bcompiler/__init__.py
bcompiler/compile.py
bcompiler/main.py
bcompiler/utils.py
bcompiler/analysers/__init__.py
bcompiler/analysers/ad_hoc.py
bcompiler/analysers/annex.py
bcompiler/analysers/financial.py
bcompiler/analysers/keyword.py
bcompiler/analysers/rcf.py
bcompiler/analysers/swimlane.py
bcompiler/analysers/swimlane_assurance.py
bcompiler/analysers/utils.py
bcompiler/api/__init__.py
bcompiler/api/api.py
bcompiler/core/__init__.py
bcompiler/core/master.py
bcompiler/core/row.py
bcompiler/core/temporal.py
bcompiler/process/__init__.py
bcompiler/process/bootstrap.py
bcompiler/process/cell.py
bcompiler/process/cellformat.py
bcompiler/process/cleansers.py
bcompiler/process/datamap.py
bcompiler/process/digest.py
bcompiler/process/simple_comparitor.py
bcompiler/process/template.py
bcompiler/templates/__init__.py
bcompiler/templates/templates.py
bcompiler/tests/__init__.py
bcompiler/tests/conftest.py
bcompiler/tests/test_annex.py
bcompiler/tests/test_bootstrap.py
bcompiler/tests/test_cleanser.py
bcompiler/tests/test_datamap.py
bcompiler/tests/test_empty_returns_dir.py
bcompiler/tests/test_encoding.py
bcompiler/tests/test_external_deps.py
bcompiler/tests/test_file_parsing.py
bcompiler/tests/test_financial_analysis.py
bcompiler/tests/test_financial_year.py
bcompiler/tests/test_integration.py
bcompiler/tests/test_master.py
bcompiler/tests/test_populate_templates.py
bcompiler/tests/test_quarter.py
bcompiler/tests/test_rcf.py
bcompiler/tests/test_row.py
bcompiler/tests/test_swimlane.py
bcompiler-1.3.23.dist-info/LICENSE
bcompiler-1.3.23.dist-info/METADATA
bcompiler-1.3.23.dist-info/WHEEL
bcompiler-1.3.23.dist-info/entry_points.txt
bcompiler-1.3.23.dist-info/top_level.txt
bcompiler-1.3.23.dist-info/RECORD
