Metadata-Version: 2.1
Name: bcompiler
Version: 1.3.23
Summary: Program to migrate data for DfT BICC reporting process.
Home-page: https://bitbucket.org/mrlemon/bcompiler
Author: Matthew Lemon
Author-email: matt@matthewlemon.com
Maintainer: Matthew Lemon
Maintainer-email: matt@matthewlemon.com
License: MIT
Keywords: data console commandline excel
Platform: UNKNOWN
Classifier: Development Status :: 3 - Alpha
Classifier: Environment :: Console
Classifier: Intended Audience :: Other Audience
Classifier: Programming Language :: Python :: 3.5
Classifier: Programming Language :: Python :: 3.6
Classifier: Topic :: Text Processing
Requires-Python: >=3.6
Requires-Dist: openpyxl (==2.6.2)
Requires-Dist: python-dateutil
Requires-Dist: colorlog
